{"stat.pickup.minecraft.wooden_slab":3,"stat.leaveGame":9,"stat.craftItem.minecraft.iron_axe":3,"stat.mineBlock.minecraft.sandstone":1120,"stat.useItem.minecraft.planks":95,"stat.pickup.minecraft.porkchop":45,"stat.useItem.minecraft.water_bucket":1,"stat.mineBlock.minecraft.stone_brick_stairs":5,"stat.pickup.minecraft.rotten_flesh":45,"stat.pickup.minecraft.sand":2762,"stat.entityKilledBy.Spider":1,"stat.useItem.minecraft.sandstone_stairs":36,"stat.craftItem.minecraft.stone_axe":2,"stat.pickup.minecraft.name_tag":3,"stat.pickup.minecraft.bucket":2,"stat.mineBlock.minecraft.wooden_slab":4,"stat.craftItem.minecraft.stone_sword":3,"stat.useItem.minecraft.anvil":1,"stat.pickup.minecraft.brown_mushroom":8,"stat.mineBlock.minecraft.sand":2138,"stat.drop.minecraft.sand":2,"stat.craftItem.minecraft.cooked_fish":3,"stat.useItem.minecraft.iron_pickaxe":3461,"stat.craftItem.minecraft.wooden_pickaxe":2,"stat.furnaceInteraction":109,"stat.killEntity.ZombieVillager":1,"stat.pickup.minecraft.beef":25,"stat.pickup.minecraft.furnace":8,"stat.useItem.minecraft.stone_stairs":13,"stat.pickup.minecraft.stone_stairs":7,"stat.useItem.minecraft.flint_and_steel":1,"stat.deaths":33,"stat.pickup.minecraft.bowl":1,"stat.pickup.minecraft.egg":12,"stat.playOneMinute":697459,"stat.craftItem.minecraft.wooden_shovel":1,"stat.craftItem.minecraft.iron_pickaxe":14,"stat.pickup.minecraft.item_frame":1,"stat.drop.minecraft.torch":2,"stat.mineBlock.minecraft.tallgrass":8,"stat.fishCaught":26,"stat.chestOpened":342,"stat.pickup.minecraft.spruce_door":1,"stat.useItem.minecraft.stone":7,"stat.pickup.minecraft.arrow":20,"stat.pickup.minecraft.waterlily":1,"stat.pickup.minecraft.wooden_pressure_plate":2,"stat.craftItem.minecraft.coal":36,"stat.fallOneCm":100772,"stat.drop.minecraft.stone_sword":1,"stat.crouchOneCm":1410,"stat.mineBlock.minecraft.chest":8,"stat.craftItem.minecraft.chest":16,"stat.craftItem.minecraft.iron_ingot":89,"stat.craftingTableInteraction":143,"stat.mineBlock.minecraft.wooden_pressure_plate":2,"stat.pickup.minecraft.milk_bucket":2,"stat.pickup.minecraft.wooden_pickaxe":1,"stat.pickup.minecraft.feather":4,"stat.useItem.minecraft.furnace":15,"stat.craftItem.minecraft.wooden_sword":3,"stat.pickup.minecraft.dye":51,"stat.pickup.minecraft.planks":87,"stat.mineBlock.minecraft.spruce_fence":1,"stat.pickup.minecraft.wheat_seeds":2,"stat.mineBlock.minecraft.gravel":51,"stat.useItem.minecraft.stone_pickaxe":1447,"stat.useItem.minecraft.stone_sword":160,"stat.mineBlock.minecraft.dirt":1303,"stat.pickup.minecraft.flint_and_steel":2,"stat.useItem.minecraft.torch":295,"stat.drop.minecraft.rotten_flesh":4,"stat.drop.minecraft.porkchop":5,"stat.craftItem.minecraft.stone_stairs":52,"stat.pickup.minecraft.crafting_table":4,"stat.useItem.minecraft.log":2,"stat.useItem.minecraft.cobblestone":96,"stat.craftItem.minecraft.crafting_table":4,"stat.mineBlock.minecraft.double_plant":11,"stat.pickup.minecraft.log":814,"stat.useItem.minecraft.cooked_fish":3,"stat.drop.minecraft.stonebrick":1,"stat.pickup.minecraft.iron_pickaxe":8,"stat.pickup.minecraft.chicken":7,"stat.pickup.minecraft.sapling":165,"stat.pickup.minecraft.apple":46,"stat.breakItem.minecraft.stone_shovel":23,"stat.drop.minecraft.bow":2,"stat.drop.minecraft.fish":17,"stat.craftItem.minecraft.bucket":1,"stat.craftItem.minecraft.planks":1252,"stat.pickup.minecraft.stone_sword":14,"stat.craftItem.minecraft.fishing_rod":2,"stat.useItem.minecraft.wooden_pressure_plate":2,"stat.useItem.minecraft.stonebrick":236,"stat.mineBlock.minecraft.log":267,"stat.useItem.minecraft.spruce_door":3,"stat.sneakTime":1291,"stat.pickup.minecraft.stone_slab":349,"stat.useItem.minecraft.wooden_axe":3,"stat.pickup.minecraft.yellow_flower":8,"stat.useItem.minecraft.fishing_rod":46,"stat.pickup.minecraft.chest":11,"stat.craftItem.minecraft.spruce_door":3,"stat.pickup.minecraft.bone":21,"stat.useItem.minecraft.iron_axe":231,"stat.drop.minecraft.stone_shovel":2,"stat.mineBlock.minecraft.cobblestone":6,"stat.pickup.minecraft.stone_pickaxe":15,"stat.craftItem.minecraft.stone_brick_stairs":52,"stat.swimOneCm":138219,"stat.climbOneCm":2974,"stat.mineBlock.minecraft.spruce_stairs":4,"stat.drop.minecraft.cobblestone":1,"stat.pickup.minecraft.cooked_porkchop":4,"stat.enderchestOpened":1,"stat.breakItem.minecraft.iron_pickaxe":12,"stat.useItem.minecraft.dirt":218,"stat.pickup.minecraft.bow":2,"stat.pickup.minecraft.iron_boots":2,"stat.craftItem.minecraft.furnace":12,"stat.craftItem.minecraft.spruce_boat":55,"stat.craftItem.minecraft.stone_pickaxe":13,"stat.pickup.minecraft.cobblestone":3199,"stat.useItem.minecraft.stone_shovel":3308,"stat.flyOneCm":250601,"stat.pickup.minecraft.sandstone":1498,"stat.pickup.minecraft.fish":25,"stat.craftItem.minecraft.wooden_slab":126,"stat.pickup.minecraft.redstone":272,"stat.mineBlock.minecraft.iron_ore":95,"stat.timeSinceDeath":29017,"stat.useItem.minecraft.wooden_slab":91,"stat.craftItem.minecraft.iron_block":3,"stat.craftItem.minecraft.stonebrick":608,"stat.pickup.minecraft.nether_wart":1,"stat.pickup.minecraft.stonebrick":180,"stat.pickup.minecraft.spruce_fence":1,"stat.drop.minecraft.dirt":2,"stat.useItem.minecraft.cooked_porkchop":5,"stat.mineBlock.minecraft.coal_ore":286,"stat.pickup.minecraft.string":15,"stat.entityKilledBy.Skeleton":5,"stat.pickup.minecraft.sandstone_stairs":4,"stat.useItem.minecraft.spruce_fence":81,"stat.sprintOneCm":830120,"stat.mineBlock.minecraft.stone_slab":24,"stat.craftItem.minecraft.stick":416,"stat.craftItem.minecraft.wooden_axe":1,"stat.useItem.minecraft.stone_slab":574,"stat.craftItem.minecraft.stone":736,"stat.mineBlock.minecraft.crafting_table":3,"stat.craftItem.minecraft.wooden_pressure_plate":2,"stat.useItem.minecraft.bucket":1,"stat.entityKilledBy.Creeper":3,"stat.mineBlock.minecraft.planks":10,"stat.drop":39,"stat.useItem.minecraft.wooden_sword":4,"stat.useItem.minecraft.ladder":2,"stat.drop.minecraft.iron_boots":1,"stat.killEntity.Zombie":10,"stat.craftItem.minecraft.sandstone_stairs":32,"stat.diveOneCm":234180,"stat.craftItem.minecraft.sandstone":216,"stat.craftItem.minecraft.ladder":51,"stat.pickup.minecraft.gravel":47,"stat.craftItem.minecraft.cooked_porkchop":8,"stat.pickup.minecraft.stone_axe":8,"stat.entityKilledBy.Guardian":4,"stat.useItem.minecraft.porkchop":1,"stat.useItem.minecraft.potion":1,"stat.useItem.minecraft.rotten_flesh":4,"stat.pickup.minecraft.stone_brick_stairs":41,"stat.pickup.minecraft.diamond_sword":1,"stat.jump":5196,"stat.useItem.minecraft.sand":1230,"stat.pickup.minecraft.coal":390,"stat.pickup.minecraft.iron_ingot":46,"stat.useItem.minecraft.stone_axe":43,"stat.pickup.minecraft.spider_eye":2,"stat.craftItem.minecraft.torch":188,"stat.pickup.minecraft.dirt":2206,"stat.pickup.minecraft.iron_ore":109,"stat.useItem.minecraft.glass":19,"stat.pickup.minecraft.stone_shovel":30,"stat.boatOneCm":424603,"stat.useItem.minecraft.sapling":1,"stat.mineBlock.minecraft.lapis_ore":8,"stat.pickup.minecraft.iron_axe":5,"stat.mineBlock.minecraft.stone_stairs":7,"stat.damageTaken":8660,"stat.pickup.minecraft.leather":15,"stat.useItem.minecraft.stone_brick_stairs":28,"stat.mineBlock.minecraft.torch":88,"stat.mineBlock.minecraft.furnace":1,"stat.useItem.minecraft.wooden_pickaxe":91,"stat.mineBlock.minecraft.sapling":9,"stat.mineBlock.minecraft.sandstone_stairs":4,"stat.entityKilledBy.Zombie":4,"stat.damageDealt":6687,"stat.craftItem.minecraft.glass":64,"stat.craftItem.minecraft.anvil":1,"stat.killEntity.Cow":7,"stat.useItem.minecraft.crafting_table":7,"stat.killEntity.Pig":12,"stat.craftItem.minecraft.stone_slab":648,"stat.craftItem.minecraft.stone_shovel":28,"stat.walkOneCm":2398549,"stat.animalsBred":2,"stat.useItem.minecraft.chest":25,"stat.pickup.minecraft.stick":106,"stat.useItem.minecraft.spruce_boat":35,"stat.breakItem.minecraft.stone_pickaxe":11,"stat.useItem.minecraft.item_frame":1,"stat.pickup.minecraft.stone":538,"stat.useItem.minecraft.spruce_stairs":37,"stat.pickup.minecraft.cooked_beef":14,"stat.pickup.minecraft.ladder":201,"stat.killEntity.Skeleton":3,"stat.mineBlock.minecraft.stonebrick":46,"stat.killEntity.Spider":6,"stat.craftItem.minecraft.spruce_fence":105,"stat.mobKills":39,"stat.breakItem.minecraft.iron_axe":1,"stat.mineBlock.minecraft.leaves":63,"stat.pickup.minecraft.torch":370,"stat.pickup.minecraft.spruce_stairs":4,"stat.mineBlock.minecraft.redstone_ore":37,"stat.craftItem.minecraft.spruce_stairs":56,"stat.mineBlock.minecraft.stone":3235,"stat.breakItem.minecraft.wooden_pickaxe":2,"stat.useItem.minecraft.sandstone":159}